udserver/.DS_Store
udserver/__init__.py
udserver/cli.py
udserver/config.cfg
udserver/config.py
udserver/udserver.py
udserver/public/.DS_Store
udserver/public/favicon.ico
udserver/public/css/.DS_Store
udserver/public/css/bootstrap.min.css
udserver/public/css/dropzone.css
udserver/public/css/upload.css
udserver/public/fonts/glyphicons-halflings-regular.eot
udserver/public/fonts/glyphicons-halflings-regular.svg
udserver/public/fonts/glyphicons-halflings-regular.ttf
udserver/public/fonts/glyphicons-halflings-regular.woff
udserver/public/fonts/glyphicons-halflings-regular.woff2
udserver/public/js/.DS_Store
udserver/public/js/bootstrap.min.js
udserver/public/js/dropzone.js
udserver/public/js/jquery-1.11.1.min.js
udserver/public/js/upload.js
udserver/templates/index.html
udserver-0.2.0.dist-info/DESCRIPTION.rst
udserver-0.2.0.dist-info/METADATA
udserver-0.2.0.dist-info/RECORD
udserver-0.2.0.dist-info/WHEEL
udserver-0.2.0.dist-info/entry_points.txt
udserver-0.2.0.dist-info/metadata.json
udserver-0.2.0.dist-info/top_level.txt
