Metadata-Version: 2.0
Name: udserver
Version: 0.2.0
Summary: (udserver) a simple upload and download server, just for temporary file transfer. No security ensurance.
Home-page: https://github.com/kedpter/udserver
Author: UNKNOWN
Author-email: 790476448@qq.com
License: MIT license
Keywords: udserver
Platform: UNKNOWN
Classifier: Development Status :: 2 - Pre-Alpha
Classifier: Intended Audience :: Developers
Classifier: License :: OSI Approved :: MIT License
Classifier: Natural Language :: English
Classifier: Programming Language :: Python :: 2
Classifier: Programming Language :: Python :: 2.7
Classifier: Programming Language :: Python :: 3
Classifier: Programming Language :: Python :: 3.4
Classifier: Programming Language :: Python :: 3.5
Classifier: Programming Language :: Python :: 3.6
Requires-Dist: Click (>=6.0)
Requires-Dist: autoflake (>=1.2)
Requires-Dist: flake8 (>=3.5.0)
Requires-Dist: pytest (>=3.6.2)
Requires-Dist: twine (>=1.11.0)
Requires-Dist: yapf (>=0.22.0)
Requires-Dist: Flask (==1.0.2)
Requires-Dist: Flask-Dropzone (==1.5.3)
